soundcloud/__init__.py
soundcloud/_asynctool.py
soundcloud/_client.py
soundcloud/_front.py
soundcloud/_models.py
soundcloud/_protocols.py
soundcloud/py.typed
soundcloud_api_client-0.1.0.dist-info/METADATA
soundcloud_api_client-0.1.0.dist-info/WHEEL
soundcloud_api_client-0.1.0.dist-info/RECORD
