Metadata-Version: 2.1
Name: soundcloud-api-client
Version: 0.1.0
Summary: Soundcloud API v2 client
Author: Félix Voituret
Author-email: contact@mazard-records.com
Requires-Python: >=3.9,<4.0
Classifier: Programming Language :: Python :: 3
Classifier: Programming Language :: Python :: 3.9
Classifier: Programming Language :: Python :: 3.10
Classifier: Programming Language :: Python :: 3.11
Requires-Dist: httpx (>=0.25.1,<0.26.0)
Requires-Dist: pydantic (>=2.4.2,<3.0.0)
